pyunit_tool/__init__.py
pyunit_tool/tool.cp37-win_amd64.pyd
pyunit_tool/tool.py
pyunit_tool-2020.2.21.dist-info/METADATA
pyunit_tool-2020.2.21.dist-info/WHEEL
pyunit_tool-2020.2.21.dist-info/top_level.txt
pyunit_tool-2020.2.21.dist-info/RECORD
